maite/__init__.py
maite/_internals/__init__.py
maite/_internals/compat.py
maite/_internals/import_utils.py
maite/_internals/interop/__init__.py
maite/_internals/interop/metrics/__init__.py
maite/_internals/interop/metrics/torchmetrics.py
maite/_internals/interop/metrics/torchmetrics_detection.py
maite/_internals/interop/models/__init__.py
maite/_internals/interop/models/yolo.py
maite/_internals/protocols/__init__.py
maite/_internals/protocols/generic.py
maite/_internals/protocols/image_classification.py
maite/_internals/protocols/image_semantic_segmentation.py
maite/_internals/protocols/object_detection.py
maite/_internals/protocols/task_aliases.py
maite/_internals/protocols/type_guards.py
maite/_internals/tasks/__init__.py
maite/_internals/tasks/generic.py
maite/_internals/testing/__init__.py
maite/_internals/testing/docs.py
maite/_internals/testing/project.py
maite/_internals/testing/pyright.py
maite/_internals/testing/pytest.py
maite/_internals/utils.py
maite/_internals/validation.py
maite/_version.py
maite/interop/__init__.py
maite/interop/metrics/__init__.py
maite/interop/metrics/torchmetrics.py
maite/interop/metrics.py
maite/interop/models/__init__.py
maite/interop/models/yolo.py
maite/interop/torchmetrics.py
maite/protocols/__init__.py
maite/protocols/generic.py
maite/protocols/image_classification.py
maite/protocols/object_detection.py
maite/py.typed
maite/tasks.py
maite/utils/__init__.py
maite/utils/validation.py
maite-0.9.2.dist-info/METADATA
maite-0.9.2.dist-info/WHEEL
maite-0.9.2.dist-info/entry_points.txt
maite-0.9.2.dist-info/licenses/LICENSE.txt
maite-0.9.2.dist-info/RECORD
