Metadata-Version: 2.4
Name: maite
Version: 0.9.2
Summary: Library of common types, protocols (a.k.a. structural subtypes), and utilities to support AI test and evaluation
License: MIT License
License-File: LICENSE.txt
Keywords: machine learning,testing,pytest
Author: MIT Lincoln Laboratory
Requires-Python: >=3.10
Classifier: Development Status :: 3 - Alpha
Classifier: License :: OSI Approved :: MIT License
Classifier: Operating System :: OS Independent
Classifier: Intended Audience :: Science/Research
Classifier: Programming Language :: Python :: 3.10
Classifier: Programming Language :: Python :: 3.11
Classifier: Programming Language :: Python :: 3.12
Classifier: Topic :: Scientific/Engineering
Classifier: Programming Language :: Python :: 3 :: Only
Provides-Extra: builddocs
Provides-Extra: dev
Provides-Extra: test
Provides-Extra: torchmetrics
Provides-Extra: yolo-models
Requires-Dist: boto3 (>=1.35) ; extra == "yolo-models"
Requires-Dist: botocore (>=1.35) ; extra == "yolo-models"
Requires-Dist: datasets (>=3) ; extra == "builddocs"
Requires-Dist: hypothesis (>=6.61.0,<=6.113) ; extra == "test"
Requires-Dist: ipykernel (==6.30.1) ; extra == "builddocs"
Requires-Dist: jupyter ; extra == "builddocs"
Requires-Dist: jupytext (>=1.14.0) ; extra == "test"
Requires-Dist: kornia ; extra == "builddocs"
Requires-Dist: matplotlib (>=3.7.1) ; extra == "yolo-models"
Requires-Dist: matplotlib ; extra == "builddocs"
Requires-Dist: nbconvert ; extra == "builddocs"
Requires-Dist: numpy (>=1.24.2)
Requires-Dist: numpydoc (>=1.5.0,!=1.10.0) ; extra == "test"
Requires-Dist: opencv-python-headless (>=4.6.0) ; extra == "yolo-models"
Requires-Dist: pandas (>=2.0) ; extra == "yolo-models"
Requires-Dist: pip ; extra == "test"
Requires-Dist: pre-commit ; extra == "dev"
Requires-Dist: pycocotools ; extra == "builddocs"
Requires-Dist: pyright (>=1.1.280,!=1.1.401) ; extra == "test"
Requires-Dist: pytest (>=7.0.0) ; extra == "builddocs"
Requires-Dist: pytest (>=7.0.0) ; extra == "test"
Requires-Dist: pytest-mock (>=3.10.0) ; extra == "test"
Requires-Dist: roboflow (>=1.1.30) ; extra == "yolo-models"
Requires-Dist: torch (>=1.7,!=1.12.0) ; extra == "builddocs"
Requires-Dist: torch (>=1.7,!=1.12.0) ; extra == "test"
Requires-Dist: torch (>=2.2.0) ; extra == "yolo-models"
Requires-Dist: torchmetrics[detection] (>=1.7.0,<2.0.0) ; extra == "torchmetrics"
Requires-Dist: torchmetrics[detection] ; extra == "builddocs"
Requires-Dist: torchvision ; extra == "builddocs"
Requires-Dist: tox (>=4.24.2,<5.0.0) ; extra == "builddocs"
Requires-Dist: tox ; extra == "dev"
Requires-Dist: transformers ; extra == "builddocs"
Requires-Dist: typing-extensions (>=4.5,!=4.6)
Requires-Dist: ultralytics (>=8.2.78) ; extra == "yolo-models"
Requires-Dist: ultralytics ; extra == "builddocs"
Requires-Dist: watermark ; extra == "builddocs"
Requires-Dist: yolov5 (>=7.0.13) ; extra == "yolo-models"
Project-URL: Bug Reports, https://github.com/mit-ll-ai-technology/maite/issues
Project-URL: Homepage, https://github.com/mit-ll-ai-technology/maite
Project-URL: Source, https://github.com/mit-ll-ai-technology/maite
